[
    {   
        "id":1,
        "first_name": "siwar",
        "last_name": "siwar",
        "email": "siwar@gmail.com",
        "password": "123",
        "subject":"informatique",
        "phonenumber":22222222
    },
    {   
        "id":1,
        "first_name": "siwar",
        "last_name": "siwar",
        "email": "siwar@gmail.com",
        "password": "123",
        "subject":"informatique",
        "phonenumber":22222222
    },
    {   
        "id":1,
        "first_name": "siwar",
        "last_name": "siwar",
        "email": "siwar@gmail.com",
        "password": "123",
        "subject":"informatique",
        "phonenumber":22222222
    },
    {   
        "id":1,
        "first_name": "siwar",
        "last_name": "siwar",
        "email": "siwar@gmail.com",
        "password": "123",
        "subject":"informatique",
        "phonenumber":22222222
    },
    {   
        "id":1,
        "first_name": "siwar",
        "last_name": "siwar",
        "email": "siwar@gmail.com",
        "password": "123",
        "subject":"informatique",
        "phonenumber":22222222
    },
    {   
        "id":1,
        "first_name": "siwar",
        "last_name": "siwar",
        "email": "siwar@gmail.com",
        "password": "123",
        "subject":"informatique",
        "phonenumber":22222222
    }
]